[{"name2":"Gustavo Parma","seller":"SebastianAlvarez","points":33},{"name2":"Cecilia Cristiano","seller":"PaoloDeFranco","points":30},{"name2":"Jair Coceres","seller":"LucasBouissa","points":29},{"name2":"Diego Scleidorovich","seller":"LucasBouissa","points":28},{"name2":"Mathias Legarreta","seller":"MathiasLegarreta","points":28},{"name2":"Ernesto RUTING","seller":"PaoloDeFranco","points":28},{"name2":"Mauricio Stagno","seller":"JavierHern\u00e1ndez","points":28},{"name2":"Gonzalo keuylian","seller":"FrankoGraziano","points":27},{"name2":"Nicolas Imbriaco","seller":"LucasBouissa","points":27},{"name2":"Sebasti\u00e1n M\u00f6ller","seller":"FedericoArmandPilon","points":26},{"name2":"Chuck Norris","seller":"FedericoArmandPilon","points":26},{"name2":"Nicol\u00e1s Moreira","seller":"Nicol\u00e1sFripp","points":26},{"name2":"Diana Gonzalez","seller":"ErnestoRoca","points":26},{"name2":"Matias Fern\u00e1ndez","seller":"Mauro","points":26},{"name2":"Mauro Padilla","seller":"Mauro","points":26},{"name2":"Matias Guigou","seller":"Mauro","points":26},{"name2":"Lenadro Veiga","seller":"AgustinPerez","points":26},{"name2":"Alex Rostan","seller":"LucasBouissa","points":25},{"name2":"Mauricio Piren\u00e9","seller":"JonathanMurana","points":25},{"name2":"Franko Graziano","seller":"FrankoGraziano","points":25},{"name2":"Pablo Alvarez","seller":"LucasBouissa","points":25},{"name2":"Nelson-Picapiedra","seller":"Galvao","points":25},{"name2":"Ignacio Alvarez","seller":"SebastianAlvarez","points":25},{"name2":"Jonnathan Silva","seller":"JavierHern\u00e1ndez","points":25},{"name2":"Mario \u00c1lvarez","seller":"SebastianAlvarez","points":24},{"name2":"Jos\u00e9 Passarini","seller":"Galvao","points":24},{"name2":"Mat\u00edas Poloni","seller":"MateoGonnet","points":24},{"name2":"Ximena Rey","seller":"JavierHern\u00e1ndez","points":24},{"name2":"Nicolas Cairus Domenech","seller":"FrankoGraziano","points":24},{"name2":"Carolina Mallo","seller":"Mauro","points":24},{"name2":"Silvia Reyes","seller":"LucasBouissa","points":24},{"name2":"Avedis Maroukian","seller":"Pancho","points":24},{"name2":"ANA LAURA NIEVES","seller":"JavierHern\u00e1ndez","points":23},{"name2":"Jose 2","seller":"Pepe","points":23},{"name2":"Agustin Perez","seller":"AgustinPerez","points":23},{"name2":"Gonzalo Lupi","seller":"Pancho","points":23},{"name2":"Luc\u00eda Ram\u00edrez","seller":"Mauro","points":23},{"name2":"Nuber Mura\u00f1a","seller":"JonathanMurana","points":23},{"name2":"Carolina Mallo","seller":"Mauro","points":23},{"name2":"Joaquin Rosas","seller":"JavierHern\u00e1ndez","points":23},{"name2":"Eliana Cuello","seller":"Galvao","points":23},{"name2":"Rafael P\u00e9rez","seller":"Mauro","points":23},{"name2":"Ernesto Roca","seller":"ErnestoRoca","points":23},{"name2":"Pablo Gaggero","seller":"JavierHern\u00e1ndez","points":23},{"name2":"Luis Pers\u00edncula","seller":"JavierHern\u00e1ndez","points":23},{"name2":"Santiago Geymonat","seller":"Nicol\u00e1sFripp","points":22},{"name2":"Mariano Mart\u00ednez","seller":"MarianoMartinez","points":22},{"name2":"Alexandrer Rodriguez","seller":"AgustinPerez","points":22},{"name2":"MA. FLORENCIA IRAOLA","seller":"PaoloDeFranco","points":22},{"name2":"Ignacio Mendez","seller":"MarianoMartinez","points":22},{"name2":"Joel Gonnet","seller":"MateoGonnet","points":22},{"name2":"Federico Fioritto","seller":"Pancho","points":22},{"name2":"Nicol\u00e1s Fripp 2","seller":"Nicol\u00e1sFripp","points":22},{"name2":"Joaqu\u00edn Duomarco","seller":"Nicol\u00e1sFripp","points":22},{"name2":"Pepe","seller":"Pepe","points":22},{"name2":"Federico Alvarez","seller":"SebastianAlvarez","points":22},{"name2":"Rafael Esponda","seller":"FedericoArmandPilon","points":22},{"name2":"Tatiana \u00c1lvarez ","seller":"JonathanMurana","points":22},{"name2":"RODRIGO CAUDULLO","seller":"FedericoArmandPilon","points":22},{"name2":"Juan Ignacio Masoller","seller":"LucasBouissa","points":21},{"name2":"Eugenia P\u00e9rez Frascheri","seller":"AgustinPerez","points":21},{"name2":"Mathias Legarreta","seller":"MathiasLegarreta","points":21},{"name2":"Ernesto Roca","seller":"ErnestoRoca","points":21},{"name2":"Facundo Borges","seller":"PaoloDeFranco","points":21},{"name2":"Hugo Alarc\u00f3n","seller":"PaoloDeFranco","points":21},{"name2":"FABIAN BRUNETTO","seller":"FrankoGraziano","points":21},{"name2":"Germ\u00e1n Fern\u00e1ndez","seller":"FrankoGraziano","points":21},{"name2":"Jose 3","seller":"Pepe","points":21},{"name2":"Galvao 2","seller":"Galvao","points":21},{"name2":"Pablo Ramos","seller":"JavierHern\u00e1ndez","points":21},{"name2":"Sof\u00eda M","seller":"Pancho","points":21},{"name2":"Ariel Fernandez","seller":"Nicol\u00e1sFripp","points":21},{"name2":"Francisco Fonseca","seller":"FrankoGraziano","points":21},{"name2":"Sof\u00eda Eugui","seller":"MateoGonnet","points":21},{"name2":"Nicolas Moscoso","seller":"Mauro","points":21},{"name2":"Daniel Laco","seller":"JavierHern\u00e1ndez","points":21},{"name2":"Mathias Legarreta","seller":"MathiasLegarreta","points":21},{"name2":"ANDRES AUDI","seller":"FrankoGraziano","points":21},{"name2":"Federico Pereira","seller":"Nicol\u00e1sFripp","points":21},{"name2":"Rodrigo Beira","seller":"Nicol\u00e1sFripp","points":21},{"name2":"Lucas Bouissa","seller":"LucasBouissa","points":21},{"name2":"MART\u00cdN ORO\u00d1O","seller":"LucasBouissa","points":21},{"name2":"Pablo Len\u00fa","seller":"JavierHern\u00e1ndez","points":21},{"name2":"Juan Cor","seller":"Nicol\u00e1sFripp","points":21},{"name2":"Gustavo Fripp","seller":"Nicol\u00e1sFripp","points":21},{"name2":"Eduardo Roriguez","seller":"LucasBouissa","points":21},{"name2":"Miguel Massa","seller":"LucasBouissa","points":21},{"name2":"Carlos Capano","seller":"FedericoArmandPilon","points":21},{"name2":"Lucas Oleaga","seller":"FedericoArmandPilon","points":21},{"name2":"Agust\u00edn Saavedra","seller":"FrankoGraziano","points":20},{"name2":"Javier G\u00f3mez Bubba","seller":"JavierHern\u00e1ndez","points":20},{"name2":"Gustavo Fonseca","seller":"FrankoGraziano","points":20},{"name2":"Mart\u00edn Biganzoli","seller":"Pancho","points":20},{"name2":"Gonzalo Martinez","seller":"Nicol\u00e1sFripp","points":20},{"name2":"Guillermina Gonnet","seller":"MateoGonnet","points":20},{"name2":"Pablo Hern\u00e1ndez","seller":"LucasBouissa","points":20},{"name2":"Andr\u00e9s Bonilla","seller":"LucasBouissa","points":20},{"name2":"CAROLINA TORTORELLA","seller":"PaoloDeFranco","points":20},{"name2":"Sebasti\u00e1n \u00c1lvarez","seller":"SebastianAlvarez","points":20},{"name2":"Agust\u00edn Menini","seller":"Galvao","points":20},{"name2":"Ricardo Calvo","seller":"LucasBouissa","points":20},{"name2":"Ignacio Martinez","seller":"LucasBouissa","points":20},{"name2":"Adri\u00e1n Bonjour","seller":"Nicol\u00e1sFripp","points":20},{"name2":"Mauro Imbriaco","seller":"Nicol\u00e1sFripp","points":20},{"name2":"Lucas Bouissa","seller":"LucasBouissa","points":20},{"name2":"RICARDO K\u00d6STER","seller":"LucasBouissa","points":20},{"name2":"Luciano Ortiz","seller":"PabloGronros","points":20},{"name2":"Agustina Pereira","seller":"Mauro","points":19},{"name2":"Javier Machado Gini","seller":"Nicol\u00e1sFripp","points":19},{"name2":"ALEJANDRO PALLEIRO","seller":"JavierHern\u00e1ndez","points":19},{"name2":"Javier Hern\u00e1ndez","seller":"JavierHern\u00e1ndez","points":19},{"name2":"Marcos Valdivia","seller":"JonathanMurana","points":19},{"name2":"mariela graziano","seller":"FrankoGraziano","points":19},{"name2":"Wilington Ruiz","seller":"LucasBouissa","points":19},{"name2":"Juan Mat\u00edas Nobre","seller":"LucasBouissa","points":19},{"name2":"Santiago Rodr\u00edguez","seller":"ErnestoRoca","points":19},{"name2":"Rodolfo Roca","seller":"ErnestoRoca","points":19},{"name2":"Jonas Mattos","seller":"JavierHern\u00e1ndez","points":19},{"name2":"Ramiro TATA Martinez","seller":"MarianoMartinez","points":19},{"name2":"Carlos Francia","seller":"Galvao","points":19},{"name2":"Juan Angel \u00c1lvarez ","seller":"JonathanMurana","points":19},{"name2":"Martin Utermark","seller":"MateoGonnet","points":19},{"name2":"Federico Porto","seller":"Pancho","points":19},{"name2":"Carla Merlano","seller":"JavierHern\u00e1ndez","points":19},{"name2":"Juan Manuel Laporte1","seller":"FedericoArmandPilon","points":18},{"name2":"MIGUEL AIRALA","seller":"PaoloDeFranco","points":18},{"name2":"Rodrigo Fernandez Erostarbe","seller":"PabloGronros","points":18},{"name2":"Nicol\u00e1s Mastandrea","seller":"Pancho","points":18},{"name2":"Mart\u00edn Biganzoli","seller":"Pancho","points":18},{"name2":"Adriana Echeverria","seller":"ErnestoRoca","points":18},{"name2":"Nicol\u00e1s Mastandrea","seller":"FrankoGraziano","points":18},{"name2":"ESTEBAN IBA\u00d1EZ","seller":"FrankoGraziano","points":18},{"name2":"Federico Doreste","seller":"Pancho","points":18},{"name2":"Felipe Santisteban","seller":"FedericoArmandPilon","points":18},{"name2":"Gonzalo L\u00f3pez Tuana","seller":"Nicol\u00e1sFripp","points":18},{"name2":"LUCIA BETANCUR 2 ","seller":"Nicol\u00e1sFripp","points":18},{"name2":"Andr\u00e9s Puig","seller":"Pancho","points":18},{"name2":"Jessica Padilla","seller":"Mauro","points":18},{"name2":"Ariel P\u00e9rez","seller":"Nicol\u00e1sFripp","points":18},{"name2":"Cardarello","seller":"Galvao","points":18},{"name2":"Virginia Olivera ","seller":"MateoGonnet","points":18},{"name2":"Mathias Legarreta","seller":"MathiasLegarreta","points":18},{"name2":"PABLO ORO\u00d1O","seller":"LucasBouissa","points":18},{"name2":"Guillermo Pizza","seller":"LucasBouissa","points":18},{"name2":"Dahiana Romero","seller":"Mauro","points":18},{"name2":"Bianca Poloni","seller":"MateoGonnet","points":18},{"name2":"Mathias Legarreta","seller":"MathiasLegarreta","points":18},{"name2":"Marcelo Minetti","seller":"Nicol\u00e1sFripp","points":18},{"name2":"Gustavo Gonzalez","seller":"JonathanMurana","points":17},{"name2":"JUAN JOSE DE LEON","seller":"JavierHern\u00e1ndez","points":17},{"name2":"Micaela_Formento","seller":"SebastianAlvarez","points":17},{"name2":"Ignacio Mendez","seller":"MarianoMartinez","points":17},{"name2":"Agust\u00edn Menini","seller":"Galvao","points":17},{"name2":"Juanma Alarcon","seller":"PaoloDeFranco","points":17},{"name2":"Maite Suarez","seller":"PaoloDeFranco","points":17},{"name2":"Sonia Magallanes","seller":"MarianoMartinez","points":17},{"name2":"Gonzalo Sintas","seller":"LucasBouissa","points":17},{"name2":"Gabriel Bulla","seller":"JavierHern\u00e1ndez","points":17},{"name2":"Martin Viurrarena","seller":"JonathanMurana","points":17},{"name2":"Federico Rosas ","seller":"JavierHern\u00e1ndez","points":17},{"name2":"Ernesto Roca","seller":"ErnestoRoca","points":17},{"name2":"Pablo Bentancour ","seller":"LucasBouissa","points":17},{"name2":"Guillermo Capano","seller":"FedericoArmandPilon","points":17},{"name2":"Ernesto Oleaga","seller":"FedericoArmandPilon","points":17},{"name2":"Daniel Losada","seller":"JavierHern\u00e1ndez","points":17},{"name2":"Diego Armand Pilon","seller":"FedericoArmandPilon","points":17},{"name2":"Anthony Villas Boas","seller":"LucasBouissa","points":17},{"name2":"eduardo martinez","seller":"FrankoGraziano","points":17},{"name2":"Ramiro Mari\u00f1o","seller":"Mauro","points":17},{"name2":"Richard Galeano","seller":"Nicol\u00e1sFripp","points":17},{"name2":"Nicol\u00e1s Fripp","seller":"Nicol\u00e1sFripp","points":17},{"name2":"FRANCO AMACORIA","seller":"Mauro","points":17},{"name2":"Mathias Legarreta","seller":"MathiasLegarreta","points":17},{"name2":"Pablo Gronros","seller":"PabloGronros","points":17},{"name2":"Chuzo Drogba","seller":"MarianoMartinez","points":16},{"name2":"LUCIANO RUIZ","seller":"FrankoGraziano","points":16},{"name2":"Luciano Ruiz","seller":"FrankoGraziano","points":16},{"name2":"Cecilia Techera","seller":"JonathanMurana","points":16},{"name2":"Gustavo Fripp","seller":"Nicol\u00e1sFripp","points":16},{"name2":"Agust\u00edn P\u00e9rez","seller":"AgustinPerez","points":16},{"name2":"Mart\u00edn de Castellet","seller":"Mauro","points":16},{"name2":"Rodrigo Viera","seller":"LucasBouissa","points":16},{"name2":"Valentina P\u00e9rez","seller":"AgustinPerez","points":16},{"name2":"Santiago Pereira","seller":"ErnestoRoca","points":16},{"name2":"Valmiro Rangel","seller":"FedericoArmandPilon","points":16},{"name2":"Federico Molinari","seller":"MathiasLegarreta","points":16},{"name2":"Nicol\u00e1s Majul Deus","seller":"Pancho","points":16},{"name2":"Santiago Gonett","seller":"Galvao","points":16},{"name2":"Martin Riveiro","seller":"Nicol\u00e1sFripp","points":16},{"name2":"Gimena Norando","seller":"JavierHern\u00e1ndez","points":16},{"name2":"SERGIO VITOLA","seller":"PaoloDeFranco","points":16},{"name2":"Ramiro \"Tata\" Mart\u00ednez","seller":"MarianoMartinez","points":16},{"name2":"NICOLAS DE LEON","seller":"JavierHern\u00e1ndez","points":15},{"name2":"Felipe Maestro","seller":"Galvao","points":15},{"name2":"Mariana Gonnet","seller":"MateoGonnet","points":15},{"name2":"Nicol\u00e1s Billar","seller":"JonathanMurana","points":15},{"name2":"Alberto Vaucheret","seller":"Nicol\u00e1sFripp","points":15},{"name2":"Natalia Domenech","seller":"FrankoGraziano","points":15},{"name2":"Rafael Gottero","seller":"FrankoGraziano","points":15},{"name2":"Santiago Armand Pilon","seller":"MateoGonnet","points":15},{"name2":"SANTIAGO LORENZELLI","seller":"AgustinPerez","points":15},{"name2":"Benjamin Machin","seller":"LucasBouissa","points":15},{"name2":"Ernesto Roca","seller":"ErnestoRoca","points":15},{"name2":"Raphael Hounie","seller":"MarianoMartinez","points":15},{"name2":"Nicolas Perez","seller":"AgustinPerez","points":15},{"name2":"Jimena Mura\u00f1a","seller":"JonathanMurana","points":15},{"name2":"Julio Martinez","seller":"MarianoMartinez","points":15},{"name2":"Jonathan Mura\u00f1a","seller":"JonathanMurana","points":15},{"name2":"Gonzalo Ingold","seller":"Nicol\u00e1sFripp","points":15},{"name2":"Gimena Rodriguez ","seller":"Mauro","points":15},{"name2":"LUCIA BETANCUR","seller":"Nicol\u00e1sFripp","points":15},{"name2":"Mayra Olivera","seller":"Galvao","points":14},{"name2":"ESTEFANIA AVILA","seller":"FrankoGraziano","points":14},{"name2":"Fernando Goldie","seller":"JavierHern\u00e1ndez","points":14},{"name2":"Garlas","seller":"Pepe","points":14},{"name2":"Valentina P\u00e9rez","seller":"AgustinPerez","points":14},{"name2":"Franco Sena","seller":"Nicol\u00e1sFripp","points":14},{"name2":"Julio Alvarez","seller":"JavierHern\u00e1ndez","points":14},{"name2":"Diana Armand Pil\u00f3n","seller":"FedericoArmandPilon","points":14},{"name2":"Lazaro Pereira","seller":"JonathanMurana","points":14},{"name2":"Alejandro Long Arnaldi","seller":"FedericoArmandPilon","points":14},{"name2":"Francisco Arnaldi","seller":"Pancho","points":14},{"name2":"PAOLO DE FRANCO","seller":"PaoloDeFranco","points":14},{"name2":"Mathias Legarreta","seller":"MathiasLegarreta","points":14},{"name2":"Juan Manuel Laporte2","seller":"FedericoArmandPilon","points":14},{"name2":"MELISA ANDREA SUAREZ LUGO","seller":"FedericoArmandPilon","points":14},{"name2":"Shirley Silvera","seller":"JonathanMurana","points":14},{"name2":"Alexandro S\u00e1nchez","seller":"Nicol\u00e1sFripp","points":14},{"name2":"Alianna Vidal","seller":"JavierHern\u00e1ndez","points":13},{"name2":"Matias Molinari","seller":"MathiasLegarreta","points":13},{"name2":"karen fernandes","seller":"PaoloDeFranco","points":13},{"name2":"Mathias Legarreta","seller":"MathiasLegarreta","points":13},{"name2":"Jose 1","seller":"Pepe","points":13},{"name2":"Esteban Roca","seller":"ErnestoRoca","points":13},{"name2":"Mateo Gonnet","seller":"MateoGonnet","points":13},{"name2":"Sebastian Silvera","seller":"JonathanMurana","points":13},{"name2":"FEDERICO ARMAND PILON","seller":"FedericoArmandPilon","points":13},{"name2":"Maite Dom\u00ednguez","seller":"MarianoMartinez","points":12},{"name2":"Gonzalo Galvao Galvete","seller":"Galvao","points":12},{"name2":"Ma. Cecilia Amorena","seller":"JavierHern\u00e1ndez","points":12},{"name2":"Marcelo Caraballo","seller":"JavierHern\u00e1ndez","points":12},{"name2":"Agustin de leon","seller":"JavierHern\u00e1ndez","points":12},{"name2":"Guzm\u00e1n Negrin","seller":"FrankoGraziano","points":11},{"name2":"Aldana Oliva Viar","seller":"Mauro","points":11},{"name2":"Gast\u00f3n Guido ","seller":"Nicol\u00e1sFripp","points":11},{"name2":"Enrique Ventura","seller":"MarianoMartinez","points":11},{"name2":"Florencia Della Santa","seller":"JavierHern\u00e1ndez","points":11},{"name2":"Germ\u00e1n Iba\u00f1ez","seller":"FrankoGraziano","points":11},{"name2":"Diego Armand Pil\u00f3n 2","seller":"FedericoArmandPilon","points":10},{"name2":"Pablo Redes","seller":"JavierHern\u00e1ndez","points":10},{"name2":"Giuliano Severi","seller":"Pancho","points":10},{"name2":"SEBASTIAN ARMAND PILON","seller":"FedericoArmandPilon","points":10},{"name2":"Giuliana Perdomo","seller":"Nicol\u00e1sFripp","points":9},{"name2":"PABLO SANTESTEBAN","seller":"FrankoGraziano","points":9},{"name2":"Alvaro Arrillaga","seller":"JavierHern\u00e1ndez","points":8},{"name2":"Mart\u00edn Biganzoli","seller":"Pancho","points":7}]